{
    "game_number": "SEA202305270",
    "date": "20230527",
    "start_time": "1:10 p.m. Local",
    "attendance": "44624",
    "venue": "T-Mobile Park",
    "game_duration": "152",
    "home_team": {
        "name": "Seattle Mariners",
        "logo": "https://cdn.ssref.net/req/202308101/tlogo/br/SEA-2023.png",
        "url": "/teams/SEA/2023.shtml",
        "runs": "5",
        "hits": "11",
        "errors": "1",
        "inning_scores": {
            "1": "3",
            "2": "1",
            "3": "0",
            "4": "0",
            "5": "0",
            "6": "0",
            "7": "1",
            "8": "0",
            "9": "X"
        },
        "batters": [
            {
                "id": "crawfjp01",
                "name": "J.P. Crawford",
                "AB": "4",
                "R": "2",
                "H": "2",
                "RBI": "0",
                "BB": "0",
                "SO": "1",
                "PA": "4",
                "BA": ".254",
                "OBP": ".364",
                "SLG": ".373",
                "OPS": ".736",
                "Pit": "14",
                "Str": "10",
                "WPA": "0.062",
                "aLI": " 0.40",
                "WPA_plus": "0.073",
                "WPA_minus": "-0.011",
                "cWPA": " 0.03%",
                "acLI": " 0.32",
                "RE24": " 0.4",
                "PO": "0",
                "A": "0",
                "Details": "2B",
                "HR": "",
                "B2": "1",
                "B3": "",
                "CS": "",
                "SB": ""
            },
            {
                "id": "francty01",
                "name": "Ty France",
                "AB": "3",
                "R": "1",
                "H": "2",
                "RBI": "1",
                "BB": "1",
                "SO": "1",
                "PA": "4",
                "BA": ".267",
                "OBP": ".348",
                "SLG": ".421",
                "OPS": ".769",
                "Pit": "20",
                "Str": "12",
                "WPA": "0.111",
                "aLI": " 0.54",
                "WPA_plus": "0.118",
                "WPA_minus": "-0.007",
                "cWPA": " 0.05%",
                "acLI": " 0.43",
                "RE24": " 1.3",
                "PO": "3",
                "A": "1",
                "Details": "2·2B",
                "HR": "",
                "B2": "2",
                "B3": "",
                "CS": "",
                "SB": ""
            },
            {
                "id": "rodriju01",
                "name": "Julio Rodríguez",
                "AB": "4",
                "R": "1",
                "H": "2",
                "RBI": "1",
                "BB": "0",
                "SO": "0",
                "PA": "4",
                "BA": ".238",
                "OBP": ".305",
                "SLG": ".422",
                "OPS": ".728",
                "Pit": "8",
                "Str": "8",
                "WPA": "0.034",
                "aLI": " 0.49",
                "WPA_plus": "0.080",
                "WPA_minus": "-0.046",
                "cWPA": " 0.02%",
                "acLI": " 0.39",
                "RE24": " 1.5",
                "PO": "0",
                "A": "0",
                "Details": "2B,SB",
                "HR": "",
                "B2": "1",
                "B3": "",
                "CS": "",
                "SB": "1"
            },
            {
                "id": "kelenja01",
                "name": "Jarred Kelenic",
                "AB": "4",
                "R": "0",
                "H": "1",
                "RBI": "0",
                "BB": "0",
                "SO": "2",
                "PA": "4",
                "BA": ".277",
                "OBP": ".330",
                "SLG": ".522",
                "OPS": ".852",
                "Pit": "17",
                "Str": "12",
                "WPA": "-0.046",
                "aLI": " 0.46",
                "WPA_plus": "0.015",
                "WPA_minus": "-0.061",
                "cWPA": "-0.02%",
                "acLI": " 0.36",
                "RE24": " -0.9",
                "PO": "1",
                "A": "0",
                "Details": "2B",
                "HR": "",
                "B2": "1",
                "B3": "",
                "CS": "",
                "SB": ""
            },
            {
                "id": "suareeu01",
                "name": "Eugenio Suárez",
                "AB": "3",
                "R": "1",
                "H": "1",
                "RBI": "2",
                "BB": "0",
                "SO": "1",
                "PA": "4",
                "BA": ".219",
                "OBP": ".323",
                "SLG": ".323",
                "OPS": ".646",
                "Pit": "13",
                "Str": "9",
                "WPA": "0.067",
                "aLI": " 0.49",
                "WPA_plus": "0.090",
                "WPA_minus": "-0.023",
                "cWPA": " 0.03%",
                "acLI": " 0.39",
                "RE24": " 0.3",
                "PO": "",
                "A": "",
                "Details": "SF",
                "HR": "",
                "B2": "",
                "B3": "",
                "CS": "",
                "SB": ""
            },
            {
                "id": "raleica01",
                "name": "Cal Raleigh",
                "AB": "4",
                "R": "0",
                "H": "1",
                "RBI": "0",
                "BB": "0",
                "SO": "0",
                "PA": "4",
                "BA": ".237",
                "OBP": ".324",
                "SLG": ".442",
                "OPS": ".766",
                "Pit": "13",
                "Str": "7",
                "WPA": "-0.010",
                "aLI": " 0.31",
                "WPA_plus": "0.018",
                "WPA_minus": "-0.028",
                "cWPA": "-0.01%",
                "acLI": " 0.24",
                "RE24": " -0.8",
                "PO": "18",
                "A": "0",
                "Details": "",
                "HR": "",
                "B2": "",
                "B3": "",
                "CS": "",
                "SB": ""
            },
            {
                "id": "hernate01",
                "name": "Teoscar Hernández",
                "AB": "4",
                "R": "0",
                "H": "1",
                "RBI": "1",
                "BB": "0",
                "SO": "1",
                "PA": "4",
                "BA": ".233",
                "OBP": ".270",
                "SLG": ".406",
                "OPS": ".676",
                "Pit": "12",
                "Str": "11",
                "WPA": "0.067",
                "aLI": " 0.42",
                "WPA_plus": "0.078",
                "WPA_minus": "-0.012",
                "cWPA": " 0.03%",
                "acLI": " 0.34",
                "RE24": " 0.5",
                "PO": "2",
                "A": "0",
                "Details": "2B",
                "HR": "",
                "B2": "1",
                "B3": "",
                "CS": "",
                "SB": ""
            },
            {
                "id": "cabaljo01",
                "name": "José Caballero",
                "AB": "4",
                "R": "0",
                "H": "1",
                "RBI": "0",
                "BB": "0",
                "SO": "1",
                "PA": "4",
                "BA": ".277",
                "OBP": ".395",
                "SLG": ".415",
                "OPS": ".810",
                "Pit": "16",
                "Str": "12",
                "WPA": "-0.029",
                "aLI": " 0.34",
                "WPA_plus": "0.006",
                "WPA_minus": "-0.035",
                "cWPA": "-0.01%",
                "acLI": " 0.27",
                "RE24": " -0.5",
                "PO": "0",
                "A": "0",
                "Details": "",
                "HR": "",
                "B2": "",
                "B3": "",
                "CS": "",
                "SB": ""
            },
            {
                "id": "wongko01",
                "name": "Kolten Wong",
                "AB": "4",
                "R": "0",
                "H": "0",
                "RBI": "0",
                "BB": "0",
                "SO": "2",
                "PA": "4",
                "BA": ".160",
                "OBP": ".250",
                "SLG": ".189",
                "OPS": ".439",
                "Pit": "21",
                "Str": "12",
                "WPA": "-0.020",
                "aLI": " 0.24",
                "WPA_plus": "0.000",
                "WPA_minus": "-0.020",
                "cWPA": "-0.01%",
                "acLI": " 0.19",
                "RE24": " -0.8",
                "PO": "2",
                "A": "2",
                "Details": "",
                "HR": "",
                "B2": "",
                "B3": "",
                "CS": "",
                "SB": ""
            },
            {
                "id": "castilu02",
                "name": "Luis Castillo",
                "AB": "",
                "R": "",
                "H": "",
                "RBI": "",
                "BB": "",
                "SO": "",
                "PA": "",
                "BA": "",
                "OBP": "",
                "SLG": "",
                "OPS": "",
                "Pit": "",
                "Str": "",
                "WPA": "",
                "aLI": "",
                "WPA_plus": "",
                "WPA_minus": "",
                "cWPA": "",
                "acLI": "",
                "RE24": "",
                "PO": "1",
                "A": "0",
                "Details": "",
                "HR": "",
                "B2": "",
                "B3": "",
                "CS": "",
                "SB": ""
            },
            {
                "id": "speiega01",
                "name": "Gabe Speier",
                "AB": "",
                "R": "",
                "H": "",
                "RBI": "",
                "BB": "",
                "SO": "",
                "PA": "",
                "BA": "",
                "OBP": "",
                "SLG": "",
                "OPS": "",
                "Pit": "",
                "Str": "",
                "WPA": "",
                "aLI": "",
                "WPA_plus": "",
                "WPA_minus": "",
                "cWPA": "",
                "acLI": "",
                "RE24": "",
                "PO": "0",
                "A": "0",
                "Details": "",
                "HR": "",
                "B2": "",
                "B3": "",
                "CS": "",
                "SB": ""
            },
            {
                "id": "brashma01",
                "name": "Matt Brash",
                "AB": "",
                "R": "",
                "H": "",
                "RBI": "",
                "BB": "",
                "SO": "",
                "PA": "",
                "BA": "",
                "OBP": "",
                "SLG": "",
                "OPS": "",
                "Pit": "",
                "Str": "",
                "WPA": "",
                "aLI": "",
                "WPA_plus": "",
                "WPA_minus": "",
                "cWPA": "",
                "acLI": "",
                "RE24": "",
                "PO": "0",
                "A": "0",
                "Details": "",
                "HR": "",
                "B2": "",
                "B3": "",
                "CS": "",
                "SB": ""
            },
            {
                "id": "gotttr01",
                "name": "Trevor Gott",
                "AB": "",
                "R": "",
                "H": "",
                "RBI": "",
                "BB": "",
                "SO": "",
                "PA": "",
                "BA": "",
                "OBP": "",
                "SLG": "",
                "OPS": "",
                "Pit": "",
                "Str": "",
                "WPA": "",
                "aLI": "",
                "WPA_plus": "",
                "WPA_minus": "",
                "cWPA": "",
                "acLI": "",
                "RE24": "",
                "PO": "0",
                "A": "0",
                "Details": "",
                "HR": "",
                "B2": "",
                "B3": "",
                "CS": "",
                "SB": ""
            },
            {
                "id": "topaju01",
                "name": "Justin Topa",
                "AB": "",
                "R": "",
                "H": "",
                "RBI": "",
                "BB": "",
                "SO": "",
                "PA": "",
                "BA": "",
                "OBP": "",
                "SLG": "",
                "OPS": "",
                "Pit": "",
                "Str": "",
                "WPA": "",
                "aLI": "",
                "WPA_plus": "",
                "WPA_minus": "",
                "cWPA": "",
                "acLI": "",
                "RE24": "",
                "PO": "0",
                "A": "0",
                "Details": "",
                "HR": "",
                "B2": "",
                "B3": "",
                "CS": "",
                "SB": ""
            }
        ],
        "pitchers": [
            {
                "id": "castilu02",
                "name": "Luis Castillo",
                "IP": " 6 ",
                "R": "0",
                "H": "1",
                "ER": "0",
                "BB": "2",
                "SO": "10",
                "HR": "0",
                "ERA": "2.69",
                "BF": "22",
                "Pit": "99",
                "Str": "64",
                "Ctct": "25",
                "StS": "24",
                "StL": "15",
                "GB": "5",
                "FB": "4",
                "LD": "2",
                "Unk": "0",
                "GSc": "78",
                "IR": "",
                "IS": "",
                "WPA": "0.219",
                "aLI": " 0.61",
                "cWPA": " 0.10%",
                "acLI": " 0.48",
                "RE24": " 2.9"
            },
            {
                "id": "speiega01",
                "name": "Gabe Speier",
                "IP": " 0.2",
                "R": "0",
                "H": "1",
                "ER": "0",
                "BB": "0",
                "SO": "1",
                "HR": "0",
                "ERA": "2.95",
                "BF": "3",
                "Pit": "9",
                "Str": "7",
                "Ctct": "2",
                "StS": "1",
                "StL": "4",
                "GB": "1",
                "FB": "1",
                "LD": "0",
                "Unk": "0",
                "GSc": "",
                "IR": "0",
                "IS": "0",
                "WPA": "0.016",
                "aLI": " 0.80",
                "cWPA": " 0.01%",
                "acLI": " 0.63",
                "RE24": " 0.3"
            },
            {
                "id": "brashma01",
                "name": "Matt Brash",
                "IP": " 0.1",
                "R": "0",
                "H": "0",
                "ER": "0",
                "BB": "0",
                "SO": "1",
                "HR": "0",
                "ERA": "4.64",
                "BF": "1",
                "Pit": "4",
                "Str": "3",
                "Ctct": "1",
                "StS": "2",
                "StL": "0",
                "GB": "0",
                "FB": "0",
                "LD": "0",
                "Unk": "0",
                "GSc": "",
                "IR": "1",
                "IS": "0",
                "WPA": "0.011",
                "aLI": " 0.40",
                "cWPA": " 0.01%",
                "acLI": " 0.32",
                "RE24": " 0.2"
            },
            {
                "id": "gotttr01",
                "name": "Trevor Gott",
                "IP": " 1 ",
                "R": "0",
                "H": "0",
                "ER": "0",
                "BB": "0",
                "SO": "2",
                "HR": "0",
                "ERA": "1.90",
                "BF": "3",
                "Pit": "12",
                "Str": "8",
                "Ctct": "2",
                "StS": "2",
                "StL": "4",
                "GB": "0",
                "FB": "1",
                "LD": "0",
                "Unk": "0",
                "GSc": "",
                "IR": "0",
                "IS": "0",
                "WPA": "0.011",
                "aLI": " 0.15",
                "cWPA": " 0.01%",
                "acLI": " 0.12",
                "RE24": " 0.5"
            },
            {
                "id": "topaju01",
                "name": "Justin Topa",
                "IP": " 1 ",
                "R": "0",
                "H": "0",
                "ER": "0",
                "BB": "1",
                "SO": "3",
                "HR": "0",
                "ERA": "2.66",
                "BF": "4",
                "Pit": "20",
                "Str": "12",
                "Ctct": "4",
                "StS": "0",
                "StL": "8",
                "GB": "0",
                "FB": "0",
                "LD": "0",
                "Unk": "0",
                "GSc": "",
                "IR": "0",
                "IS": "0",
                "WPA": "0.006",
                "aLI": " 0.19",
                "cWPA": " 0.00%",
                "acLI": " 0.15",
                "RE24": " 0.5"
            }
        ]
    },
    "away_team": {
        "name": "Pittsburgh Pirates",
        "logo": "https://cdn.ssref.net/req/202308101/tlogo/br/PIT-2023.png",
        "url": "/teams/PIT/2023.shtml",
        "runs": "0",
        "hits": "2",
        "errors": "2",
        "inning_scores": {
            "1": "0",
            "2": "0",
            "3": "0",
            "4": "0",
            "5": "0",
            "6": "0",
            "7": "0",
            "8": "0",
            "9": "0"
        },
        "batters": [
            {
                "id": "marcatu01",
                "name": "Tucupita Marcano",
                "AB": "4",
                "R": "0",
                "H": "1",
                "RBI": "0",
                "BB": "0",
                "SO": "1",
                "PA": "4",
                "BA": ".265",
                "OBP": ".337",
                "SLG": ".470",
                "OPS": ".807",
                "Pit": "13",
                "Str": "10",
                "WPA": "0.032",
                "aLI": " 0.48",
                "WPA_plus": "0.060",
                "WPA_minus": "-0.029",
                "cWPA": " 0.02%",
                "acLI": " 0.54",
                "RE24": " 0.1",
                "PO": "1",
                "A": "1",
                "Details": "2B",
                "HR": "",
                "B2": "1",
                "B3": "",
                "CS": "",
                "SB": ""
            },
            {
                "id": "reynobr01",
                "name": "Bryan Reynolds",
                "AB": "3",
                "R": "0",
                "H": "0",
                "RBI": "0",
                "BB": "1",
                "SO": "2",
                "PA": "4",
                "BA": ".287",
                "OBP": ".341",
                "SLG": ".505",
                "OPS": ".847",
                "Pit": "21",
                "Str": "11",
                "WPA": "-0.050",
                "aLI": " 0.54",
                "WPA_plus": "0.009",
                "WPA_minus": "-0.059",
                "cWPA": "-0.03%",
                "acLI": " 0.61",
                "RE24": " -0.6",
                "PO": "2",
                "A": "0",
                "Details": "",
                "HR": "",
                "B2": "",
                "B3": "",
                "CS": "",
                "SB": ""
            },
            {
                "id": "joeco01",
                "name": "Connor Joe",
                "AB": "3",
                "R": "0",
                "H": "0",
                "RBI": "0",
                "BB": "1",
                "SO": "1",
                "PA": "4",
                "BA": ".250",
                "OBP": ".348",
                "SLG": ".471",
                "OPS": ".819",
                "Pit": "18",
                "Str": "10",
                "WPA": "-0.052",
                "aLI": " 0.59",
                "WPA_plus": "0.007",
                "WPA_minus": "-0.059",
                "cWPA": "-0.03%",
                "acLI": " 0.66",
                "RE24": " -0.3",
                "PO": "4",
                "A": "1",
                "Details": "",
                "HR": "",
                "B2": "",
                "B3": "",
                "CS": "",
                "SB": ""
            },
            {
                "id": "santaca01",
                "name": "Carlos Santana",
                "AB": "4",
                "R": "0",
                "H": "0",
                "RBI": "0",
                "BB": "0",
                "SO": "3",
                "PA": "4",
                "BA": ".229",
                "OBP": ".322",
                "SLG": ".360",
                "OPS": ".682",
                "Pit": "17",
                "Str": "12",
                "WPA": "-0.061",
                "aLI": " 0.58",
                "WPA_plus": "0.000",
                "WPA_minus": "-0.061",
                "cWPA": "-0.04%",
                "acLI": " 0.65",
                "RE24": " -1.0",
                "PO": "",
                "A": "",
                "Details": "",
                "HR": "",
                "B2": "",
                "B3": "",
                "CS": "",
                "SB": ""
            },
            {
                "id": "suwinja01",
                "name": "Jack Suwinski",
                "AB": "4",
                "R": "0",
                "H": "1",
                "RBI": "0",
                "BB": "0",
                "SO": "3",
                "PA": "4",
                "BA": ".234",
                "OBP": ".348",
                "SLG": ".482",
                "OPS": ".829",
                "Pit": "16",
                "Str": "13",
                "WPA": "-0.009",
                "aLI": " 0.49",
                "WPA_plus": "0.027",
                "WPA_minus": "-0.035",
                "cWPA": "-0.01%",
                "acLI": " 0.55",
                "RE24": " -0.3",
                "PO": "3",
                "A": "0",
                "Details": "",
                "HR": "",
                "B2": "",
                "B3": "",
                "CS": "",
                "SB": ""
            },
            {
                "id": "hayeske01",
                "name": "Ke'Bryan Hayes",
                "AB": "4",
                "R": "0",
                "H": "0",
                "RBI": "0",
                "BB": "0",
                "SO": "3",
                "PA": "4",
                "BA": ".226",
                "OBP": ".282",
                "SLG": ".353",
                "OPS": ".634",
                "Pit": "15",
                "Str": "10",
                "WPA": "-0.045",
                "aLI": " 0.48",
                "WPA_plus": "0.000",
                "WPA_minus": "-0.045",
                "cWPA": "-0.03%",
                "acLI": " 0.54",
                "RE24": " -0.8",
                "PO": "1",
                "A": "3",
                "Details": "",
                "HR": "",
                "B2": "",
                "B3": "",
                "CS": "",
                "SB": ""
            },
            {
                "id": "baeji01",
                "name": "Ji Hwan Bae",
                "AB": "1",
                "R": "0",
                "H": "0",
                "RBI": "0",
                "BB": "0",
                "SO": "0",
                "PA": "2",
                "BA": ".269",
                "OBP": ".324",
                "SLG": ".358",
                "OPS": ".682",
                "Pit": "5",
                "Str": "3",
                "WPA": "0.005",
                "aLI": " 0.54",
                "WPA_plus": "0.021",
                "WPA_minus": "-0.016",
                "cWPA": " 0.00%",
                "acLI": " 0.61",
                "RE24": " 0.0",
                "PO": "1",
                "A": "0",
                "Details": "SB,HBP",
                "HR": "",
                "B2": "",
                "B3": "",
                "CS": "",
                "SB": "1"
            },
            {
                "id": "castrro01",
                "name": "Rodolfo Castro",
                "AB": "1",
                "R": "0",
                "H": "0",
                "RBI": "0",
                "BB": "0",
                "SO": "1",
                "PA": "1",
                "BA": ".261",
                "OBP": ".363",
                "SLG": ".435",
                "OPS": ".798",
                "Pit": "3",
                "Str": "3",
                "WPA": "-0.018",
                "aLI": " 0.73",
                "WPA_plus": "0.000",
                "WPA_minus": "-0.018",
                "cWPA": "-0.01%",
                "acLI": " 0.82",
                "RE24": " -0.3",
                "PO": "0",
                "A": "0",
                "Details": "",
                "HR": "",
                "B2": "",
                "B3": "",
                "CS": "",
                "SB": ""
            },
            {
                "id": "palacjo01",
                "name": "Josh Palacios",
                "AB": "2",
                "R": "0",
                "H": "0",
                "RBI": "0",
                "BB": "0",
                "SO": "0",
                "PA": "2",
                "BA": ".250",
                "OBP": ".286",
                "SLG": ".250",
                "OPS": ".536",
                "Pit": "12",
                "Str": "6",
                "WPA": "-0.039",
                "aLI": " 0.74",
                "WPA_plus": "0.000",
                "WPA_minus": "-0.039",
                "cWPA": "-0.03%",
                "acLI": " 0.83",
                "RE24": " -0.5",
                "PO": "1",
                "A": "0",
                "Details": "",
                "HR": "",
                "B2": "",
                "B3": "",
                "CS": "",
                "SB": ""
            },
            {
                "id": "mccutan01",
                "name": "Andrew McCutchen",
                "AB": "1",
                "R": "0",
                "H": "0",
                "RBI": "0",
                "BB": "0",
                "SO": "1",
                "PA": "1",
                "BA": ".268",
                "OBP": ".362",
                "SLG": ".459",
                "OPS": ".821",
                "Pit": "4",
                "Str": "3",
                "WPA": "-0.011",
                "aLI": " 0.40",
                "WPA_plus": "0.000",
                "WPA_minus": "-0.011",
                "cWPA": "-0.01%",
                "acLI": " 0.45",
                "RE24": " -0.2",
                "PO": "0",
                "A": "0",
                "Details": "",
                "HR": "",
                "B2": "",
                "B3": "",
                "CS": "",
                "SB": ""
            },
            {
                "id": "delayja01",
                "name": "Jason Delay",
                "AB": "2",
                "R": "0",
                "H": "0",
                "RBI": "0",
                "BB": "1",
                "SO": "2",
                "PA": "3",
                "BA": ".318",
                "OBP": ".370",
                "SLG": ".455",
                "OPS": ".824",
                "Pit": "20",
                "Str": "13",
                "WPA": "-0.015",
                "aLI": " 0.38",
                "WPA_plus": "0.008",
                "WPA_minus": "-0.023",
                "cWPA": "-0.01%",
                "acLI": " 0.43",
                "RE24": " -0.3",
                "PO": "10",
                "A": "0",
                "Details": "",
                "HR": "",
                "B2": "",
                "B3": "",
                "CS": "",
                "SB": ""
            },
            {
                "id": "velasvi01",
                "name": "Vince Velasquez",
                "AB": "",
                "R": "",
                "H": "",
                "RBI": "",
                "BB": "",
                "SO": "",
                "PA": "",
                "BA": "",
                "OBP": "",
                "SLG": "",
                "OPS": "",
                "Pit": "",
                "Str": "",
                "WPA": "",
                "aLI": "",
                "WPA_plus": "",
                "WPA_minus": "",
                "cWPA": "",
                "acLI": "",
                "RE24": "",
                "PO": "0",
                "A": "0",
                "Details": "",
                "HR": "",
                "B2": "",
                "B3": "",
                "CS": "",
                "SB": ""
            },
            {
                "id": "hernajo03",
                "name": "Jose Hernandez",
                "AB": "",
                "R": "",
                "H": "",
                "RBI": "",
                "BB": "",
                "SO": "",
                "PA": "",
                "BA": "",
                "OBP": "",
                "SLG": "",
                "OPS": "",
                "Pit": "",
                "Str": "",
                "WPA": "",
                "aLI": "",
                "WPA_plus": "",
                "WPA_minus": "",
                "cWPA": "",
                "acLI": "",
                "RE24": "",
                "PO": "0",
                "A": "0",
                "Details": "",
                "HR": "",
                "B2": "",
                "B3": "",
                "CS": "",
                "SB": ""
            },
            {
                "id": "zastrro01",
                "name": "Rob Zastryzny",
                "AB": "",
                "R": "",
                "H": "",
                "RBI": "",
                "BB": "",
                "SO": "",
                "PA": "",
                "BA": "",
                "OBP": "",
                "SLG": "",
                "OPS": "",
                "Pit": "",
                "Str": "",
                "WPA": "",
                "aLI": "",
                "WPA_plus": "",
                "WPA_minus": "",
                "cWPA": "",
                "acLI": "",
                "RE24": "",
                "PO": "0",
                "A": "0",
                "Details": "",
                "HR": "",
                "B2": "",
                "B3": "",
                "CS": "",
                "SB": ""
            },
            {
                "id": "moretda01",
                "name": "Dauri Moreta",
                "AB": "",
                "R": "",
                "H": "",
                "RBI": "",
                "BB": "",
                "SO": "",
                "PA": "",
                "BA": "",
                "OBP": "",
                "SLG": "",
                "OPS": "",
                "Pit": "",
                "Str": "",
                "WPA": "",
                "aLI": "",
                "WPA_plus": "",
                "WPA_minus": "",
                "cWPA": "",
                "acLI": "",
                "RE24": "",
                "PO": "1",
                "A": "0",
                "Details": "",
                "HR": "",
                "B2": "",
                "B3": "",
                "CS": "",
                "SB": ""
            },
            {
                "id": "bednada01",
                "name": "David Bednar",
                "AB": "",
                "R": "",
                "H": "",
                "RBI": "",
                "BB": "",
                "SO": "",
                "PA": "",
                "BA": "",
                "OBP": "",
                "SLG": "",
                "OPS": "",
                "Pit": "",
                "Str": "",
                "WPA": "",
                "aLI": "",
                "WPA_plus": "",
                "WPA_minus": "",
                "cWPA": "",
                "acLI": "",
                "RE24": "",
                "PO": "0",
                "A": "0",
                "Details": "",
                "HR": "",
                "B2": "",
                "B3": "",
                "CS": "",
                "SB": ""
            }
        ],
        "pitchers": [
            {
                "id": "velasvi01",
                "name": "Vince Velasquez",
                "IP": " 2 ",
                "R": "4",
                "H": "7",
                "ER": "4",
                "BB": "1",
                "SO": "3",
                "HR": "0",
                "ERA": "3.86",
                "BF": "14",
                "Pit": "53",
                "Str": "34",
                "Ctct": "19",
                "StS": "6",
                "StL": "9",
                "GB": "2",
                "FB": "8",
                "LD": "4",
                "Unk": "0",
                "GSc": "28",
                "IR": "",
                "IS": "",
                "WPA": "-0.278",
                "aLI": " 0.83",
                "cWPA": "-0.19%",
                "acLI": " 0.93",
                "RE24": " -3.0"
            },
            {
                "id": "hernajo03",
                "name": "Jose Hernandez",
                "IP": " 3 ",
                "R": "0",
                "H": "2",
                "ER": "0",
                "BB": "0",
                "SO": "2",
                "HR": "0",
                "ERA": "2.38",
                "BF": "11",
                "Pit": "34",
                "Str": "25",
                "Ctct": "14",
                "StS": "5",
                "StL": "6",
                "GB": "5",
                "FB": "4",
                "LD": "2",
                "Unk": "0",
                "GSc": "",
                "IR": "0",
                "IS": "0",
                "WPA": "0.043",
                "aLI": " 0.23",
                "cWPA": " 0.03%",
                "acLI": " 0.27",
                "RE24": " 1.5"
            },
            {
                "id": "zastrro01",
                "name": "Rob Zastryzny",
                "IP": " 0.2",
                "R": "0",
                "H": "1",
                "ER": "0",
                "BB": "0",
                "SO": "1",
                "HR": "0",
                "ERA": "6.48",
                "BF": "3",
                "Pit": "12",
                "Str": "9",
                "Ctct": "3",
                "StS": "2",
                "StL": "4",
                "GB": "2",
                "FB": "0",
                "LD": "0",
                "Unk": "0",
                "GSc": "",
                "IR": "0",
                "IS": "0",
                "WPA": "0.003",
                "aLI": " 0.21",
                "cWPA": " 0.00%",
                "acLI": " 0.23",
                "RE24": " 0.2"
            },
            {
                "id": "moretda01",
                "name": "Dauri Moreta",
                "IP": " 1.1",
                "R": "1",
                "H": "1",
                "ER": "0",
                "BB": "0",
                "SO": "2",
                "HR": "0",
                "ERA": "1.90",
                "BF": "5",
                "Pit": "17",
                "Str": "12",
                "Ctct": "5",
                "StS": "5",
                "StL": "2",
                "GB": "1",
                "FB": "2",
                "LD": "1",
                "Unk": "0",
                "GSc": "",
                "IR": "1",
                "IS": "0",
                "WPA": "-0.005",
                "aLI": " 0.07",
                "cWPA": "-0.00%",
                "acLI": " 0.08",
                "RE24": " -0.2"
            },
            {
                "id": "bednada01",
                "name": "David Bednar",
                "IP": " 1 ",
                "R": "0",
                "H": "0",
                "ER": "0",
                "BB": "0",
                "SO": "1",
                "HR": "0",
                "ERA": "1.42",
                "BF": "3",
                "Pit": "18",
                "Str": "13",
                "Ctct": "9",
                "StS": "1",
                "StL": "3",
                "GB": "0",
                "FB": "2",
                "LD": "0",
                "Unk": "0",
                "GSc": "",
                "IR": "0",
                "IS": "0",
                "WPA": "0.001",
                "aLI": " 0.02",
                "cWPA": " 0.00%",
                "acLI": " 0.02",
                "RE24": " 0.5"
            }
        ]
    }
}